cloud_compose_image-0.2.0-py3.8-nspkg.pth
cloudcompose/image/__init__.py
cloudcompose/image/aws/__init__.py
cloudcompose/image/aws/cloudcontroller.py
cloudcompose/image/commands/__init__.py
cloudcompose/image/commands/cli.py
cloud_compose_image-0.2.0.dist-info/LICENSE.txt
cloud_compose_image-0.2.0.dist-info/METADATA
cloud_compose_image-0.2.0.dist-info/WHEEL
cloud_compose_image-0.2.0.dist-info/namespace_packages.txt
cloud_compose_image-0.2.0.dist-info/top_level.txt
cloud_compose_image-0.2.0.dist-info/RECORD
