Metadata-Version: 2.1
Name: cloud-compose-image
Version: 0.2.0
Summary: UNKNOWN
Home-page: https://github.com/cloud-compose/cloud-compose-image
Author: Patrick Cullen and the WaPo platform tools team
Author-email: opensource@washingtonpost.com
License: UNKNOWN
Download-URL: https://github.com/cloud-compose/cloud-compose-image/tarball/v0.1.3
Keywords: cloud,compose,aws
Platform: UNKNOWN
Requires-Dist: click (>=6.6)
Requires-Dist: boto3 (>=1.3.1)
Requires-Dist: botocore (>=1.4.14)
Requires-Dist: docutils (>=0.12)
Requires-Dist: futures (>=3.0.5)
Requires-Dist: Jinja2 (>=2.8)
Requires-Dist: jmespath (>=0.9.0)
Requires-Dist: MarkupSafe (>=0.23)
Requires-Dist: cloud-compose (>=0.3.0)
Requires-Dist: python-dateutil (>=2.5.3)
Requires-Dist: PyYAML (>=3.11)
Requires-Dist: retrying (>=1.3.3)
Requires-Dist: six (>=1.10.0)
